tempdisagg/__init__.py
tempdisagg/core/__init__.py
tempdisagg/core/numeric_utils.py
tempdisagg/core/rho_optimizer.py
tempdisagg/core/temporal_aggregator.py
tempdisagg/model/__init__.py
tempdisagg/model/models_handler.py
tempdisagg/model/tempdisagg_adjuster.py
tempdisagg/model/tempdisagg_base.py
tempdisagg/model/tempdisagg_core.py
tempdisagg/model/tempdisagg_ensemble.py
tempdisagg/model/tempdisagg_fitter.py
tempdisagg/model/tempdisagg_model.py
tempdisagg/model/tempdisagg_summary.py
tempdisagg/model/tempdisagg_visualizer.py
tempdisagg/postprocessing/__init__.py
tempdisagg/postprocessing/ensemble_prediction.py
tempdisagg/postprocessing/post_estimation.py
tempdisagg/preprocessing/__init__.py
tempdisagg/preprocessing/conversion_matrix_builder.py
tempdisagg/preprocessing/disagg_input_preparer.py
tempdisagg/preprocessing/input_preprocessor.py
tempdisagg/preprocessing/timeseries_completer.py
tempdisagg/utils/__init__.py
tempdisagg/utils/logging_utils.py
tempdisagg/utils/retropolarizer.py
tempdisagg-0.2.13.dist-info/licenses/LICENSE
tempdisagg-0.2.13.dist-info/METADATA
tempdisagg-0.2.13.dist-info/WHEEL
tempdisagg-0.2.13.dist-info/top_level.txt
tempdisagg-0.2.13.dist-info/RECORD
