Metadata-Version: 2.4
Name: tempdisagg
Version: 0.2.13
Summary: Temporal disaggregation models in Python
Author-email: Jaime Vera-Jaramillo <jaimevera1107@gmail.com>
License-Expression: MIT
Project-URL: Homepage, https://github.com/jaimevera1107/tempdisagg
Keywords: temporal disaggregation,time series,econometrics,interpolation
Classifier: Development Status :: 4 - Beta
Classifier: Intended Audience :: Science/Research
Classifier: Programming Language :: Python :: 3
Classifier: Programming Language :: Python :: 3.8
Classifier: Operating System :: OS Independent
Requires-Python: >=3.8
License-File: LICENSE
Requires-Dist: numpy>=1.21
Requires-Dist: pandas>=1.3
Requires-Dist: scipy>=1.7
Requires-Dist: matplotlib>=3.4
Requires-Dist: scikit-learn<2.0,>=1.6
Dynamic: license-file
